Metadata-Version: 2.1
Name: valdezdf
Version: 0.0.1
Summary: Some tweaks and stuff to be more productive
Home-page: UNKNOWN
Author: Omar Valdez
Author-email: info@valdezdata.com
License: MIT
Keywords: view_df
Platform: UNKNOWN
Classifier: Development Status :: 5 - Production/Stable
Classifier: Intended Audience :: Education
Classifier: Operating System :: Microsoft :: Windows :: Windows 10
Classifier: License :: OSI Approved :: MIT License
Classifier: Programming Language :: Python :: 3
License-File: LICENCE.txt
